with_time/__init__.py
with_time/exceptions.py
with_time/timeout.py
with_time/timer.py
with_time-0.3.dist-info/AUTHORS.rst
with_time-0.3.dist-info/LICENSE
with_time-0.3.dist-info/METADATA
with_time-0.3.dist-info/WHEEL
with_time-0.3.dist-info/top_level.txt
with_time-0.3.dist-info/RECORD
