Metadata-Version: 2.1
Name: with-time
Version: 0.3
Summary: Measuring and managing of time through context-managers and decorators.
Home-page: https://github.com/IlyaSukhanov/with-time
Author: Ilya Sukhanov
Author-email: ilya@sukhanov.net
License: MIT license
Keywords: with_time
Platform: UNKNOWN
Classifier: Intended Audience :: Developers
Classifier: License :: OSI Approved :: MIT License
Classifier: Natural Language :: English
Classifier: Programming Language :: Python :: 3
Classifier: Programming Language :: Python :: 3.9
License-File: LICENSE
License-File: AUTHORS.rst
Provides-Extra: testing
Requires-Dist: pip (~=20.3) ; extra == 'testing'
Requires-Dist: flake8 ; extra == 'testing'
Requires-Dist: tox ; extra == 'testing'
Requires-Dist: coverage ; extra == 'testing'
Requires-Dist: pytest ; extra == 'testing'
Requires-Dist: pyflakes ; extra == 'testing'
Requires-Dist: pytest-cov ; extra == 'testing'
Requires-Dist: bandit ; extra == 'testing'
Requires-Dist: black (~=21.5b1) ; extra == 'testing'
Requires-Dist: isort ; extra == 'testing'
Requires-Dist: wheel ; extra == 'testing'
Requires-Dist: twine ; extra == 'testing'
Requires-Dist: rstcheck ; extra == 'testing'
